dockerspawner/__init__.py
dockerspawner/_version.py
dockerspawner/dockerspawner.py
dockerspawner/swarmspawner.py
dockerspawner/systemuserspawner.py
dockerspawner/volumenamingstrategy.py
dockerspawner-13.0.0.dist-info/LICENSE
dockerspawner-13.0.0.dist-info/METADATA
dockerspawner-13.0.0.dist-info/WHEEL
dockerspawner-13.0.0.dist-info/entry_points.txt
dockerspawner-13.0.0.dist-info/top_level.txt
dockerspawner-13.0.0.dist-info/RECORD
